{
    "name": "QUALCOMM Incorporated",
    "label": "QCOM",
    "data": [
        {
            "date": "12/08/2023",
            "open": "131.22"
        },
        {
            "date": "12/07/2023",
            "open": "131.33"
        },
        {
            "date": "12/06/2023",
            "open": "131.98"
        },
        {
            "date": "12/05/2023",
            "open": "129.09"
        },
        {
            "date": "12/04/2023",
            "open": "129.33"
        },
        {
            "date": "12/01/2023",
            "open": "129.06"
        },
        {
            "date": "11/30/2023",
            "open": "129.27"
        },
        {
            "date": "11/29/2023",
            "open": "129.24"
        },
        {
            "date": "11/28/2023",
            "open": "127.20"
        },
        {
            "date": "11/27/2023",
            "open": "127.27"
        },
        {
            "date": "11/24/2023",
            "open": "128.23"
        },
        {
            "date": "11/22/2023",
            "open": "127.89"
        },
        {
            "date": "11/21/2023",
            "open": "126.89"
        },
        {
            "date": "11/20/2023",
            "open": "129.44"
        },
        {
            "date": "11/17/2023",
            "open": "129.30"
        },
        {
            "date": "11/16/2023",
            "open": "129.09"
        },
        {
            "date": "11/15/2023",
            "open": "127.92"
        },
        {
            "date": "11/14/2023",
            "open": "127.34"
        },
        {
            "date": "11/13/2023",
            "open": "124.00"
        },
        {
            "date": "11/10/2023",
            "open": "121.90"
        },
        {
            "date": "11/09/2023",
            "open": "121.12"
        },
        {
            "date": "11/08/2023",
            "open": "121.40"
        },
        {
            "date": "11/07/2023",
            "open": "119.85"
        },
        {
            "date": "11/06/2023",
            "open": "120.00"
        },
        {
            "date": "11/03/2023",
            "open": "117.95"
        },
        {
            "date": "11/02/2023",
            "open": "117.97"
        },
        {
            "date": "11/01/2023",
            "open": "109.17"
        },
        {
            "date": "10/31/2023",
            "open": "108.30"
        },
        {
            "date": "10/30/2023",
            "open": "106.71"
        },
        {
            "date": "10/27/2023",
            "open": "106.90"
        },
        {
            "date": "10/26/2023",
            "open": "104.75"
        },
        {
            "date": "10/25/2023",
            "open": "108.81"
        },
        {
            "date": "10/24/2023",
            "open": "109.30"
        },
        {
            "date": "10/23/2023",
            "open": "107.94"
        },
        {
            "date": "10/20/2023",
            "open": "111.52"
        },
        {
            "date": "10/19/2023",
            "open": "112.39"
        },
        {
            "date": "10/18/2023",
            "open": "111.06"
        },
        {
            "date": "10/17/2023",
            "open": "108.81"
        },
        {
            "date": "10/16/2023",
            "open": "109.09"
        },
        {
            "date": "10/13/2023",
            "open": "111.72"
        },
        {
            "date": "10/12/2023",
            "open": "111.98"
        },
        {
            "date": "10/11/2023",
            "open": "112.28"
        },
        {
            "date": "10/10/2023",
            "open": "111.50"
        },
        {
            "date": "10/09/2023",
            "open": "110.32"
        },
        {
            "date": "10/06/2023",
            "open": "110.87"
        },
        {
            "date": "10/05/2023",
            "open": "109.70"
        },
        {
            "date": "10/04/2023",
            "open": "110.80"
        },
        {
            "date": "10/03/2023",
            "open": "110.81"
        },
        {
            "date": "10/02/2023",
            "open": "110.40"
        },
        {
            "date": "09/29/2023",
            "open": "111.88"
        },
        {
            "date": "09/28/2023",
            "open": "109.76"
        },
        {
            "date": "09/27/2023",
            "open": "110.73"
        },
        {
            "date": "09/26/2023",
            "open": "109.85"
        },
        {
            "date": "09/25/2023",
            "open": "106.84"
        },
        {
            "date": "09/22/2023",
            "open": "108.77"
        },
        {
            "date": "09/21/2023",
            "open": "107.98"
        },
        {
            "date": "09/20/2023",
            "open": "111.74"
        },
        {
            "date": "09/19/2023",
            "open": "112.20"
        },
        {
            "date": "09/18/2023",
            "open": "112.89"
        },
        {
            "date": "09/15/2023",
            "open": "113.97"
        },
        {
            "date": "09/14/2023",
            "open": "113.77"
        },
        {
            "date": "09/13/2023",
            "open": "111.58"
        },
        {
            "date": "09/12/2023",
            "open": "109.58"
        },
        {
            "date": "09/11/2023",
            "open": "111.27"
        },
        {
            "date": "09/08/2023",
            "open": "106.17"
        },
        {
            "date": "09/07/2023",
            "open": "110.60"
        },
        {
            "date": "09/06/2023",
            "open": "116.00"
        },
        {
            "date": "09/05/2023",
            "open": "114.91"
        },
        {
            "date": "09/01/2023",
            "open": "115.70"
        },
        {
            "date": "08/31/2023",
            "open": "112.434"
        },
        {
            "date": "08/30/2023",
            "open": "112.56"
        },
        {
            "date": "08/29/2023",
            "open": "110.52"
        },
        {
            "date": "08/28/2023",
            "open": "111.30"
        },
        {
            "date": "08/25/2023",
            "open": "108.89"
        },
        {
            "date": "08/24/2023",
            "open": "112.16"
        },
        {
            "date": "08/23/2023",
            "open": "109.34"
        },
        {
            "date": "08/22/2023",
            "open": "111.47"
        },
        {
            "date": "08/21/2023",
            "open": "109.84"
        },
        {
            "date": "08/18/2023",
            "open": "108.82"
        },
        {
            "date": "08/17/2023",
            "open": "110.19"
        },
        {
            "date": "08/16/2023",
            "open": "111.35"
        },
        {
            "date": "08/15/2023",
            "open": "113.34"
        },
        {
            "date": "08/14/2023",
            "open": "113.88"
        },
        {
            "date": "08/11/2023",
            "open": "114.125"
        },
        {
            "date": "08/10/2023",
            "open": "117.68"
        },
        {
            "date": "08/09/2023",
            "open": "117.225"
        },
        {
            "date": "08/08/2023",
            "open": "117.00"
        },
        {
            "date": "08/07/2023",
            "open": "122.21"
        },
        {
            "date": "08/04/2023",
            "open": "117.76"
        },
        {
            "date": "08/03/2023",
            "open": "116.965"
        },
        {
            "date": "08/02/2023",
            "open": "130.20"
        },
        {
            "date": "08/01/2023",
            "open": "131.92"
        },
        {
            "date": "07/31/2023",
            "open": "129.99"
        },
        {
            "date": "07/28/2023",
            "open": "128.30"
        },
        {
            "date": "07/27/2023",
            "open": "126.56"
        },
        {
            "date": "07/26/2023",
            "open": "123.20"
        },
        {
            "date": "07/25/2023",
            "open": "124.20"
        },
        {
            "date": "07/24/2023",
            "open": "124.72"
        },
        {
            "date": "07/21/2023",
            "open": "121.93"
        },
        {
            "date": "07/20/2023",
            "open": "123.52"
        },
        {
            "date": "07/19/2023",
            "open": "125.34"
        },
        {
            "date": "07/18/2023",
            "open": "122.32"
        },
        {
            "date": "07/17/2023",
            "open": "122.33"
        },
        {
            "date": "07/14/2023",
            "open": "123.00"
        },
        {
            "date": "07/13/2023",
            "open": "120.00"
        },
        {
            "date": "07/12/2023",
            "open": "117.56"
        },
        {
            "date": "07/11/2023",
            "open": "117.80"
        },
        {
            "date": "07/10/2023",
            "open": "116.47"
        },
        {
            "date": "07/07/2023",
            "open": "115.37"
        },
        {
            "date": "07/06/2023",
            "open": "115.16"
        },
        {
            "date": "07/05/2023",
            "open": "119.02"
        },
        {
            "date": "07/03/2023",
            "open": "119.27"
        },
        {
            "date": "06/30/2023",
            "open": "119.60"
        },
        {
            "date": "06/29/2023",
            "open": "117.56"
        },
        {
            "date": "06/28/2023",
            "open": "117.02"
        },
        {
            "date": "06/27/2023",
            "open": "116.74"
        },
        {
            "date": "06/26/2023",
            "open": "114.56"
        },
        {
            "date": "06/23/2023",
            "open": "114.09"
        },
        {
            "date": "06/22/2023",
            "open": "116.01"
        },
        {
            "date": "06/21/2023",
            "open": "118.61"
        },
        {
            "date": "06/20/2023",
            "open": "121.94"
        },
        {
            "date": "06/16/2023",
            "open": "124.59"
        },
        {
            "date": "06/15/2023",
            "open": "121.58"
        },
        {
            "date": "06/14/2023",
            "open": "124.35"
        },
        {
            "date": "06/13/2023",
            "open": "124.28"
        },
        {
            "date": "06/12/2023",
            "open": "121.04"
        },
        {
            "date": "06/09/2023",
            "open": "117.488"
        },
        {
            "date": "06/08/2023",
            "open": "115.60"
        },
        {
            "date": "06/07/2023",
            "open": "116.63"
        },
        {
            "date": "06/06/2023",
            "open": "112.58"
        },
        {
            "date": "06/05/2023",
            "open": "115.43"
        },
        {
            "date": "06/02/2023",
            "open": "117.24"
        },
        {
            "date": "06/01/2023",
            "open": "114.56"
        },
        {
            "date": "05/31/2023",
            "open": "113.56"
        },
        {
            "date": "05/30/2023",
            "open": "114.50"
        },
        {
            "date": "05/26/2023",
            "open": "104.94"
        },
        {
            "date": "05/25/2023",
            "open": "101.93"
        },
        {
            "date": "05/24/2023",
            "open": "102.08"
        },
        {
            "date": "05/23/2023",
            "open": "104.07"
        },
        {
            "date": "05/22/2023",
            "open": "103.672"
        },
        {
            "date": "05/19/2023",
            "open": "106.95"
        },
        {
            "date": "05/18/2023",
            "open": "104.81"
        },
        {
            "date": "05/17/2023",
            "open": "104.19"
        },
        {
            "date": "05/16/2023",
            "open": "105.67"
        },
        {
            "date": "05/15/2023",
            "open": "103.76"
        },
        {
            "date": "05/12/2023",
            "open": "104.47"
        },
        {
            "date": "05/11/2023",
            "open": "106.29"
        },
        {
            "date": "05/10/2023",
            "open": "107.00"
        },
        {
            "date": "05/09/2023",
            "open": "107.00"
        },
        {
            "date": "05/08/2023",
            "open": "108.375"
        },
        {
            "date": "05/05/2023",
            "open": "108.21"
        },
        {
            "date": "05/04/2023",
            "open": "104.03"
        },
        {
            "date": "05/03/2023",
            "open": "116.66"
        },
        {
            "date": "05/02/2023",
            "open": "116.13"
        },
        {
            "date": "05/01/2023",
            "open": "117.21"
        },
        {
            "date": "04/28/2023",
            "open": "115.095"
        },
        {
            "date": "04/27/2023",
            "open": "113.88"
        },
        {
            "date": "04/26/2023",
            "open": "114.29"
        },
        {
            "date": "04/25/2023",
            "open": "116.74"
        },
        {
            "date": "04/24/2023",
            "open": "117.82"
        },
        {
            "date": "04/21/2023",
            "open": "117.87"
        },
        {
            "date": "04/20/2023",
            "open": "117.29"
        },
        {
            "date": "04/19/2023",
            "open": "117.25"
        },
        {
            "date": "04/18/2023",
            "open": "120.34"
        },
        {
            "date": "04/17/2023",
            "open": "119.13"
        },
        {
            "date": "04/14/2023",
            "open": "120.87"
        },
        {
            "date": "04/13/2023",
            "open": "120.05"
        },
        {
            "date": "04/12/2023",
            "open": "124.41"
        },
        {
            "date": "04/11/2023",
            "open": "125.25"
        },
        {
            "date": "04/10/2023",
            "open": "122.09"
        },
        {
            "date": "04/06/2023",
            "open": "122.34"
        },
        {
            "date": "04/05/2023",
            "open": "121.42"
        },
        {
            "date": "04/04/2023",
            "open": "124.93"
        },
        {
            "date": "04/03/2023",
            "open": "126.99"
        },
        {
            "date": "03/31/2023",
            "open": "126.65"
        },
        {
            "date": "03/30/2023",
            "open": "127.08"
        },
        {
            "date": "03/29/2023",
            "open": "123.42"
        },
        {
            "date": "03/28/2023",
            "open": "123.60"
        },
        {
            "date": "03/27/2023",
            "open": "125.74"
        },
        {
            "date": "03/24/2023",
            "open": "123.63"
        },
        {
            "date": "03/23/2023",
            "open": "123.935"
        },
        {
            "date": "03/22/2023",
            "open": "124.00"
        },
        {
            "date": "03/21/2023",
            "open": "122.988"
        },
        {
            "date": "03/20/2023",
            "open": "120.77"
        },
        {
            "date": "03/17/2023",
            "open": "120.78"
        },
        {
            "date": "03/16/2023",
            "open": "117.00"
        },
        {
            "date": "03/15/2023",
            "open": "115.25"
        },
        {
            "date": "03/14/2023",
            "open": "116.41"
        },
        {
            "date": "03/13/2023",
            "open": "113.76"
        },
        {
            "date": "03/10/2023",
            "open": "117.54"
        },
        {
            "date": "03/09/2023",
            "open": "121.28"
        },
        {
            "date": "03/08/2023",
            "open": "119.55"
        },
        {
            "date": "03/07/2023",
            "open": "122.48"
        },
        {
            "date": "03/06/2023",
            "open": "124.28"
        },
        {
            "date": "03/03/2023",
            "open": "123.99"
        },
        {
            "date": "03/02/2023",
            "open": "122.16"
        },
        {
            "date": "03/01/2023",
            "open": "123.78"
        },
        {
            "date": "02/28/2023",
            "open": "123.62"
        },
        {
            "date": "02/27/2023",
            "open": "126.50"
        },
        {
            "date": "02/24/2023",
            "open": "124.24"
        },
        {
            "date": "02/23/2023",
            "open": "126.61"
        },
        {
            "date": "02/22/2023",
            "open": "124.32"
        },
        {
            "date": "02/21/2023",
            "open": "125.46"
        },
        {
            "date": "02/17/2023",
            "open": "129.50"
        },
        {
            "date": "02/16/2023",
            "open": "130.75"
        },
        {
            "date": "02/15/2023",
            "open": "130.60"
        },
        {
            "date": "02/14/2023",
            "open": "129.20"
        },
        {
            "date": "02/13/2023",
            "open": "129.46"
        },
        {
            "date": "02/10/2023",
            "open": "129.29"
        },
        {
            "date": "02/09/2023",
            "open": "133.89"
        },
        {
            "date": "02/08/2023",
            "open": "135.31"
        },
        {
            "date": "02/07/2023",
            "open": "133.15"
        },
        {
            "date": "02/06/2023",
            "open": "132.27"
        },
        {
            "date": "02/03/2023",
            "open": "131.16"
        },
        {
            "date": "02/02/2023",
            "open": "138.46"
        },
        {
            "date": "02/01/2023",
            "open": "132.68"
        },
        {
            "date": "01/31/2023",
            "open": "131.325"
        },
        {
            "date": "01/30/2023",
            "open": "131.05"
        },
        {
            "date": "01/27/2023",
            "open": "131.49"
        },
        {
            "date": "01/26/2023",
            "open": "134.405"
        },
        {
            "date": "01/25/2023",
            "open": "128.45"
        },
        {
            "date": "01/24/2023",
            "open": "130.55"
        },
        {
            "date": "01/23/2023",
            "open": "126.54"
        },
        {
            "date": "01/20/2023",
            "open": "118.42"
        },
        {
            "date": "01/19/2023",
            "open": "121.06"
        },
        {
            "date": "01/18/2023",
            "open": "121.62"
        },
        {
            "date": "01/17/2023",
            "open": "119.735"
        },
        {
            "date": "01/13/2023",
            "open": "119.82"
        },
        {
            "date": "01/12/2023",
            "open": "119.24"
        },
        {
            "date": "01/11/2023",
            "open": "117.44"
        },
        {
            "date": "01/10/2023",
            "open": "114.02"
        },
        {
            "date": "01/09/2023",
            "open": "116.73"
        },
        {
            "date": "01/06/2023",
            "open": "110.96"
        },
        {
            "date": "01/05/2023",
            "open": "109.93"
        },
        {
            "date": "01/04/2023",
            "open": "109.80"
        },
        {
            "date": "01/03/2023",
            "open": "111.35"
        },
        {
            "date": "12/30/2022",
            "open": "107.97"
        },
        {
            "date": "12/29/2022",
            "open": "108.35"
        },
        {
            "date": "12/28/2022",
            "open": "108.87"
        },
        {
            "date": "12/27/2022",
            "open": "109.75"
        },
        {
            "date": "12/23/2022",
            "open": "109.70"
        },
        {
            "date": "12/22/2022",
            "open": "112.57"
        },
        {
            "date": "12/21/2022",
            "open": "112.76"
        },
        {
            "date": "12/20/2022",
            "open": "111.40"
        },
        {
            "date": "12/19/2022",
            "open": "114.01"
        },
        {
            "date": "12/16/2022",
            "open": "116.08"
        },
        {
            "date": "12/15/2022",
            "open": "120.25"
        },
        {
            "date": "12/14/2022",
            "open": "124.23"
        },
        {
            "date": "12/13/2022",
            "open": "126.98"
        },
        {
            "date": "12/12/2022",
            "open": "116.06"
        },
        {
            "date": "12/09/2022",
            "open": "120.405"
        },
        {
            "date": "12/08/2022",
            "open": "118.98"
        },
        {
            "date": "12/07/2022",
            "open": "118.50"
        },
        {
            "date": "12/06/2022",
            "open": "122.82"
        },
        {
            "date": "12/05/2022",
            "open": "124.58"
        },
        {
            "date": "12/02/2022",
            "open": "123.71"
        },
        {
            "date": "12/01/2022",
            "open": "126.72"
        },
        {
            "date": "11/30/2022",
            "open": "118.75"
        },
        {
            "date": "11/29/2022",
            "open": "120.14"
        },
        {
            "date": "11/28/2022",
            "open": "122.16"
        },
        {
            "date": "11/25/2022",
            "open": "124.86"
        },
        {
            "date": "11/23/2022",
            "open": "123.54"
        },
        {
            "date": "11/22/2022",
            "open": "120.84"
        },
        {
            "date": "11/21/2022",
            "open": "121.09"
        },
        {
            "date": "11/18/2022",
            "open": "124.04"
        },
        {
            "date": "11/17/2022",
            "open": "118.95"
        },
        {
            "date": "11/16/2022",
            "open": "123.20"
        },
        {
            "date": "11/15/2022",
            "open": "125.65"
        },
        {
            "date": "11/14/2022",
            "open": "120.74"
        },
        {
            "date": "11/11/2022",
            "open": "118.99"
        },
        {
            "date": "11/10/2022",
            "open": "115.91"
        },
        {
            "date": "11/09/2022",
            "open": "111.46"
        },
        {
            "date": "11/08/2022",
            "open": "111.57"
        },
        {
            "date": "11/07/2022",
            "open": "107.48"
        },
        {
            "date": "11/04/2022",
            "open": "106.61"
        },
        {
            "date": "11/03/2022",
            "open": "104.38"
        },
        {
            "date": "11/02/2022",
            "open": "118.71"
        },
        {
            "date": "11/01/2022",
            "open": "119.74"
        },
        {
            "date": "10/31/2022",
            "open": "118.13"
        },
        {
            "date": "10/28/2022",
            "open": "114.17"
        },
        {
            "date": "10/27/2022",
            "open": "119.315"
        },
        {
            "date": "10/26/2022",
            "open": "118.04"
        },
        {
            "date": "10/25/2022",
            "open": "116.57"
        },
        {
            "date": "10/24/2022",
            "open": "116.34"
        },
        {
            "date": "10/21/2022",
            "open": "111.75"
        },
        {
            "date": "10/20/2022",
            "open": "113.165"
        },
        {
            "date": "10/19/2022",
            "open": "110.86"
        },
        {
            "date": "10/18/2022",
            "open": "114.95"
        },
        {
            "date": "10/17/2022",
            "open": "113.92"
        },
        {
            "date": "10/14/2022",
            "open": "114.63"
        },
        {
            "date": "10/13/2022",
            "open": "105.38"
        },
        {
            "date": "10/12/2022",
            "open": "110.32"
        },
        {
            "date": "10/11/2022",
            "open": "112.00"
        },
        {
            "date": "10/10/2022",
            "open": "120.59"
        },
        {
            "date": "10/07/2022",
            "open": "122.62"
        },
        {
            "date": "10/06/2022",
            "open": "124.51"
        },
        {
            "date": "10/05/2022",
            "open": "120.88"
        },
        {
            "date": "10/04/2022",
            "open": "120.40"
        },
        {
            "date": "10/03/2022",
            "open": "114.99"
        },
        {
            "date": "09/30/2022",
            "open": "113.76"
        },
        {
            "date": "09/29/2022",
            "open": "117.28"
        },
        {
            "date": "09/28/2022",
            "open": "118.58"
        },
        {
            "date": "09/27/2022",
            "open": "121.56"
        },
        {
            "date": "09/26/2022",
            "open": "121.54"
        },
        {
            "date": "09/23/2022",
            "open": "122.34"
        },
        {
            "date": "09/22/2022",
            "open": "124.75"
        },
        {
            "date": "09/21/2022",
            "open": "125.44"
        },
        {
            "date": "09/20/2022",
            "open": "125.74"
        },
        {
            "date": "09/19/2022",
            "open": "123.62"
        },
        {
            "date": "09/16/2022",
            "open": "124.12"
        },
        {
            "date": "09/15/2022",
            "open": "126.70"
        },
        {
            "date": "09/14/2022",
            "open": "126.27"
        },
        {
            "date": "09/13/2022",
            "open": "128.38"
        },
        {
            "date": "09/12/2022",
            "open": "133.00"
        },
        {
            "date": "09/09/2022",
            "open": "130.68"
        },
        {
            "date": "09/08/2022",
            "open": "127.47"
        },
        {
            "date": "09/07/2022",
            "open": "127.47"
        },
        {
            "date": "09/06/2022",
            "open": "128.84"
        },
        {
            "date": "09/02/2022",
            "open": "131.64"
        },
        {
            "date": "09/01/2022",
            "open": "129.98"
        },
        {
            "date": "08/31/2022",
            "open": "133.79"
        },
        {
            "date": "08/30/2022",
            "open": "137.80"
        },
        {
            "date": "08/29/2022",
            "open": "137.81"
        },
        {
            "date": "08/26/2022",
            "open": "146.16"
        },
        {
            "date": "08/25/2022",
            "open": "142.34"
        },
        {
            "date": "08/24/2022",
            "open": "140.25"
        },
        {
            "date": "08/23/2022",
            "open": "142.09"
        },
        {
            "date": "08/22/2022",
            "open": "145.30"
        },
        {
            "date": "08/19/2022",
            "open": "149.29"
        },
        {
            "date": "08/18/2022",
            "open": "148.07"
        },
        {
            "date": "08/17/2022",
            "open": "148.23"
        },
        {
            "date": "08/16/2022",
            "open": "151.45"
        },
        {
            "date": "08/15/2022",
            "open": "150.32"
        },
        {
            "date": "08/12/2022",
            "open": "148.00"
        },
        {
            "date": "08/11/2022",
            "open": "148.31"
        },
        {
            "date": "08/10/2022",
            "open": "145.85"
        },
        {
            "date": "08/09/2022",
            "open": "145.59"
        },
        {
            "date": "08/08/2022",
            "open": "149.81"
        },
        {
            "date": "08/05/2022",
            "open": "148.57"
        },
        {
            "date": "08/04/2022",
            "open": "148.68"
        },
        {
            "date": "08/03/2022",
            "open": "147.66"
        },
        {
            "date": "08/02/2022",
            "open": "145.69"
        },
        {
            "date": "08/01/2022",
            "open": "144.31"
        },
        {
            "date": "07/29/2022",
            "open": "144.595"
        },
        {
            "date": "07/28/2022",
            "open": "149.78"
        },
        {
            "date": "07/27/2022",
            "open": "151.525"
        },
        {
            "date": "07/26/2022",
            "open": "152.62"
        },
        {
            "date": "07/25/2022",
            "open": "152.80"
        },
        {
            "date": "07/22/2022",
            "open": "155.66"
        },
        {
            "date": "07/21/2022",
            "open": "152.88"
        },
        {
            "date": "07/20/2022",
            "open": "147.43"
        },
        {
            "date": "07/19/2022",
            "open": "144.14"
        },
        {
            "date": "07/18/2022",
            "open": "145.97"
        },
        {
            "date": "07/15/2022",
            "open": "143.76"
        },
        {
            "date": "07/14/2022",
            "open": "134.94"
        },
        {
            "date": "07/13/2022",
            "open": "130.55"
        },
        {
            "date": "07/12/2022",
            "open": "133.74"
        },
        {
            "date": "07/11/2022",
            "open": "133.59"
        },
        {
            "date": "07/08/2022",
            "open": "132.52"
        },
        {
            "date": "07/07/2022",
            "open": "130.65"
        },
        {
            "date": "07/06/2022",
            "open": "126.06"
        },
        {
            "date": "07/05/2022",
            "open": "121.10"
        },
        {
            "date": "07/01/2022",
            "open": "125.75"
        },
        {
            "date": "06/30/2022",
            "open": "127.61"
        },
        {
            "date": "06/29/2022",
            "open": "130.08"
        },
        {
            "date": "06/28/2022",
            "open": "129.78"
        },
        {
            "date": "06/27/2022",
            "open": "126.20"
        },
        {
            "date": "06/24/2022",
            "open": "122.38"
        },
        {
            "date": "06/23/2022",
            "open": "122.75"
        },
        {
            "date": "06/22/2022",
            "open": "121.80"
        },
        {
            "date": "06/21/2022",
            "open": "123.77"
        },
        {
            "date": "06/17/2022",
            "open": "121.42"
        },
        {
            "date": "06/16/2022",
            "open": "126.26"
        },
        {
            "date": "06/15/2022",
            "open": "131.67"
        },
        {
            "date": "06/14/2022",
            "open": "130.21"
        },
        {
            "date": "06/13/2022",
            "open": "130.59"
        },
        {
            "date": "06/10/2022",
            "open": "134.75"
        },
        {
            "date": "06/09/2022",
            "open": "137.77"
        },
        {
            "date": "06/08/2022",
            "open": "140.746"
        },
        {
            "date": "06/07/2022",
            "open": "139.13"
        },
        {
            "date": "06/06/2022",
            "open": "144.95"
        },
        {
            "date": "06/03/2022",
            "open": "142.18"
        },
        {
            "date": "06/02/2022",
            "open": "140.26"
        },
        {
            "date": "06/01/2022",
            "open": "142.55"
        },
        {
            "date": "05/31/2022",
            "open": "139.50"
        },
        {
            "date": "05/27/2022",
            "open": "136.10"
        },
        {
            "date": "05/26/2022",
            "open": "130.01"
        },
        {
            "date": "05/25/2022",
            "open": "127.80"
        },
        {
            "date": "05/24/2022",
            "open": "130.34"
        },
        {
            "date": "05/23/2022",
            "open": "129.95"
        },
        {
            "date": "05/20/2022",
            "open": "132.88"
        },
        {
            "date": "05/19/2022",
            "open": "130.45"
        },
        {
            "date": "05/18/2022",
            "open": "136.83"
        },
        {
            "date": "05/17/2022",
            "open": "137.252"
        },
        {
            "date": "05/16/2022",
            "open": "133.98"
        },
        {
            "date": "05/13/2022",
            "open": "134.29"
        },
        {
            "date": "05/12/2022",
            "open": "131.00"
        },
        {
            "date": "05/11/2022",
            "open": "135.03"
        },
        {
            "date": "05/10/2022",
            "open": "139.50"
        },
        {
            "date": "05/09/2022",
            "open": "137.99"
        },
        {
            "date": "05/06/2022",
            "open": "141.248"
        },
        {
            "date": "05/05/2022",
            "open": "146.98"
        },
        {
            "date": "05/04/2022",
            "open": "144.58"
        },
        {
            "date": "05/03/2022",
            "open": "144.705"
        },
        {
            "date": "05/02/2022",
            "open": "140.60"
        },
        {
            "date": "04/29/2022",
            "open": "145.81"
        },
        {
            "date": "04/28/2022",
            "open": "142.87"
        },
        {
            "date": "04/27/2022",
            "open": "130.815"
        },
        {
            "date": "04/26/2022",
            "open": "135.02"
        },
        {
            "date": "04/25/2022",
            "open": "131.32"
        },
        {
            "date": "04/22/2022",
            "open": "136.13"
        },
        {
            "date": "04/21/2022",
            "open": "142.34"
        },
        {
            "date": "04/20/2022",
            "open": "143.21"
        },
        {
            "date": "04/19/2022",
            "open": "138.83"
        },
        {
            "date": "04/18/2022",
            "open": "135.62"
        },
        {
            "date": "04/14/2022",
            "open": "141.05"
        },
        {
            "date": "04/13/2022",
            "open": "137.54"
        },
        {
            "date": "04/12/2022",
            "open": "137.92"
        },
        {
            "date": "04/11/2022",
            "open": "134.292"
        },
        {
            "date": "04/08/2022",
            "open": "138.54"
        },
        {
            "date": "04/07/2022",
            "open": "139.79"
        },
        {
            "date": "04/06/2022",
            "open": "142.90"
        },
        {
            "date": "04/05/2022",
            "open": "151.81"
        },
        {
            "date": "04/04/2022",
            "open": "147.74"
        },
        {
            "date": "04/01/2022",
            "open": "151.94"
        },
        {
            "date": "03/31/2022",
            "open": "152.885"
        },
        {
            "date": "03/30/2022",
            "open": "159.39"
        },
        {
            "date": "03/29/2022",
            "open": "161.21"
        },
        {
            "date": "03/28/2022",
            "open": "156.50"
        },
        {
            "date": "03/25/2022",
            "open": "157.97"
        },
        {
            "date": "03/24/2022",
            "open": "154.30"
        },
        {
            "date": "03/23/2022",
            "open": "156.11"
        },
        {
            "date": "03/22/2022",
            "open": "155.45"
        },
        {
            "date": "03/21/2022",
            "open": "153.99"
        },
        {
            "date": "03/18/2022",
            "open": "152.52"
        },
        {
            "date": "03/17/2022",
            "open": "149.19"
        },
        {
            "date": "03/16/2022",
            "open": "146.965"
        },
        {
            "date": "03/15/2022",
            "open": "142.50"
        },
        {
            "date": "03/14/2022",
            "open": "150.80"
        },
        {
            "date": "03/11/2022",
            "open": "157.95"
        },
        {
            "date": "03/10/2022",
            "open": "154.04"
        },
        {
            "date": "03/09/2022",
            "open": "156.01"
        },
        {
            "date": "03/08/2022",
            "open": "150.66"
        },
        {
            "date": "03/07/2022",
            "open": "162.32"
        },
        {
            "date": "03/04/2022",
            "open": "163.85"
        },
        {
            "date": "03/03/2022",
            "open": "170.67"
        },
        {
            "date": "03/02/2022",
            "open": "165.25"
        },
        {
            "date": "03/01/2022",
            "open": "170.96"
        },
        {
            "date": "02/28/2022",
            "open": "168.30"
        },
        {
            "date": "02/25/2022",
            "open": "167.61"
        },
        {
            "date": "02/24/2022",
            "open": "156.89"
        },
        {
            "date": "02/23/2022",
            "open": "166.65"
        },
        {
            "date": "02/22/2022",
            "open": "164.059"
        },
        {
            "date": "02/18/2022",
            "open": "167.47"
        },
        {
            "date": "02/17/2022",
            "open": "169.875"
        },
        {
            "date": "02/16/2022",
            "open": "170.68"
        },
        {
            "date": "02/15/2022",
            "open": "169.00"
        },
        {
            "date": "02/14/2022",
            "open": "165.35"
        },
        {
            "date": "02/11/2022",
            "open": "174.70"
        },
        {
            "date": "02/10/2022",
            "open": "179.40"
        },
        {
            "date": "02/09/2022",
            "open": "181.40"
        },
        {
            "date": "02/08/2022",
            "open": "174.305"
        },
        {
            "date": "02/07/2022",
            "open": "179.665"
        },
        {
            "date": "02/04/2022",
            "open": "178.99"
        },
        {
            "date": "02/03/2022",
            "open": "180.80"
        },
        {
            "date": "02/02/2022",
            "open": "180.94"
        },
        {
            "date": "02/01/2022",
            "open": "176.4447"
        },
        {
            "date": "01/31/2022",
            "open": "167.06"
        },
        {
            "date": "01/28/2022",
            "open": "162.01"
        },
        {
            "date": "01/27/2022",
            "open": "169.31"
        },
        {
            "date": "01/26/2022",
            "open": "168.58"
        },
        {
            "date": "01/25/2022",
            "open": "166.17"
        },
        {
            "date": "01/24/2022",
            "open": "162.18"
        },
        {
            "date": "01/21/2022",
            "open": "166.24"
        },
        {
            "date": "01/20/2022",
            "open": "174.53"
        },
        {
            "date": "01/19/2022",
            "open": "180.57"
        },
        {
            "date": "01/18/2022",
            "open": "185.87"
        },
        {
            "date": "01/14/2022",
            "open": "182.80"
        },
        {
            "date": "01/13/2022",
            "open": "188.70"
        },
        {
            "date": "01/12/2022",
            "open": "186.60"
        },
        {
            "date": "01/11/2022",
            "open": "179.19"
        },
        {
            "date": "01/10/2022",
            "open": "178.27"
        },
        {
            "date": "01/07/2022",
            "open": "186.60"
        },
        {
            "date": "01/06/2022",
            "open": "184.52"
        },
        {
            "date": "01/05/2022",
            "open": "186.50"
        },
        {
            "date": "01/04/2022",
            "open": "187.00"
        },
        {
            "date": "01/03/2022",
            "open": "182.91"
        },
        {
            "date": "12/31/2021",
            "open": "183.31"
        },
        {
            "date": "12/30/2021",
            "open": "185.88"
        },
        {
            "date": "12/29/2021",
            "open": "184.685"
        },
        {
            "date": "12/28/2021",
            "open": "186.59"
        },
        {
            "date": "12/27/2021",
            "open": "183.21"
        },
        {
            "date": "12/23/2021",
            "open": "181.53"
        },
        {
            "date": "12/22/2021",
            "open": "179.00"
        },
        {
            "date": "12/21/2021",
            "open": "179.38"
        },
        {
            "date": "12/20/2021",
            "open": "174.29"
        },
        {
            "date": "12/17/2021",
            "open": "175.725"
        },
        {
            "date": "12/16/2021",
            "open": "190.304"
        },
        {
            "date": "12/15/2021",
            "open": "183.97"
        },
        {
            "date": "12/14/2021",
            "open": "181.20"
        },
        {
            "date": "12/13/2021",
            "open": "186.85"
        },
        {
            "date": "12/10/2021",
            "open": "185.55"
        }
    ]
}